credold/__init__.py
credold/credold.py
credold/local_storage.py
credold/s3_storage.py
credold/storage.py
test/__init__.py
test/test_local_storage.py
test/test_s3_storage.py
credold-0.1.2.dist-info/METADATA
credold-0.1.2.dist-info/WHEEL
credold-0.1.2.dist-info/top_level.txt
credold-0.1.2.dist-info/RECORD
