Metadata-Version: 2.1
Name: credold
Version: 0.1.2
Summary: A package for managing credentials
Home-page: https://github.com/koboriakira/credold
Author: Akira Kobori
Author-email: private.beats@gmail.com
Classifier: Programming Language :: Python :: 3
Classifier: License :: OSI Approved :: MIT License
Classifier: Operating System :: OS Independent
Requires-Python: >=3.11
Requires-Dist: boto3
